streamlit_elements/__init__.py
streamlit_elements/version.py
streamlit_elements/core/__init__.py
streamlit_elements/core/callback.py
streamlit_elements/core/element.py
streamlit_elements/core/exceptions.py
streamlit_elements/core/frame.py
streamlit_elements/core/render.py
streamlit_elements/frontend/build/404.html
streamlit_elements/frontend/build/index.html
streamlit_elements/frontend/build/_next/static/ARJAwAe-WZvyC-AlnoyHy/_buildManifest.js
streamlit_elements/frontend/build/_next/static/ARJAwAe-WZvyC-AlnoyHy/_middlewareManifest.js
streamlit_elements/frontend/build/_next/static/ARJAwAe-WZvyC-AlnoyHy/_ssgManifest.js
streamlit_elements/frontend/build/_next/static/IXcKeA61wtw5kDM16t3eO/_buildManifest.js
streamlit_elements/frontend/build/_next/static/IXcKeA61wtw5kDM16t3eO/_middlewareManifest.js
streamlit_elements/frontend/build/_next/static/IXcKeA61wtw5kDM16t3eO/_ssgManifest.js
streamlit_elements/frontend/build/_next/static/KNI6uAX9p5KBOqCId9fg_/_buildManifest.js
streamlit_elements/frontend/build/_next/static/KNI6uAX9p5KBOqCId9fg_/_middlewareManifest.js
streamlit_elements/frontend/build/_next/static/KNI6uAX9p5KBOqCId9fg_/_ssgManifest.js
streamlit_elements/frontend/build/_next/static/PQL4ukHN40mxMvUgUOUHF/_buildManifest.js
streamlit_elements/frontend/build/_next/static/PQL4ukHN40mxMvUgUOUHF/_middlewareManifest.js
streamlit_elements/frontend/build/_next/static/PQL4ukHN40mxMvUgUOUHF/_ssgManifest.js
streamlit_elements/frontend/build/_next/static/VT819DgtkUU8AroyQnaRU/_buildManifest.js
streamlit_elements/frontend/build/_next/static/VT819DgtkUU8AroyQnaRU/_middlewareManifest.js
streamlit_elements/frontend/build/_next/static/VT819DgtkUU8AroyQnaRU/_ssgManifest.js
streamlit_elements/frontend/build/_next/static/a9-A9cy88i-Xxd55sTTLI/_buildManifest.js
streamlit_elements/frontend/build/_next/static/a9-A9cy88i-Xxd55sTTLI/_middlewareManifest.js
streamlit_elements/frontend/build/_next/static/a9-A9cy88i-Xxd55sTTLI/_ssgManifest.js
streamlit_elements-0.1.0.dist-info/LICENSE
streamlit_elements-0.1.0.dist-info/METADATA
streamlit_elements-0.1.0.dist-info/WHEEL
streamlit_elements-0.1.0.dist-info/top_level.txt
streamlit_elements-0.1.0.dist-info/RECORD
